artella/__init__.py
artella/plugins/__init__.py
artella/plugins/uninstaller/__init__.py
artella/plugins/uninstaller/__version__.py
artella/plugins/uninstaller/_version.py
artella/plugins/uninstaller/artella-plugin.json
artella/plugins/uninstaller/uninstaller.py
artella/plugins/uninstaller/maya/__init__.py
artella/plugins/uninstaller/maya/uninstaller.py
artella/plugins/uninstaller/resources/uninstaller.png
tests/__init__.py
tests/test_plugin.py
artella_plugins_uninstaller-1.0.4.dist-info/METADATA
artella_plugins_uninstaller-1.0.4.dist-info/WHEEL
artella_plugins_uninstaller-1.0.4.dist-info/top_level.txt
artella_plugins_uninstaller-1.0.4.dist-info/RECORD
