Metadata-Version: 2.1
Name: artella-plugins-uninstaller
Version: 1.0.4
Summary: Artella Plugin that allows to uninstall Artella DCC plugin in an easy way.
Home-page: https://github.com/artella/artella-plugins-uninstaller
Author: Artella, Inc
Author-email: support@artella.com
License: UNKNOWN
Platform: UNKNOWN
Requires-Dist: artella-plugins-core
Provides-Extra: dev
Requires-Dist: wheel ; extra == 'dev'
Provides-Extra: test
Requires-Dist: pytest ; extra == 'test'
